youtrack_sdk/__init__.py
youtrack_sdk/client.py
youtrack_sdk/entities.py
youtrack_sdk/exceptions.py
youtrack_sdk/helpers.py
youtrack_sdk/types.py
youtrack_sdk-1.0.202509091024.dist-info/LICENSE
youtrack_sdk-1.0.202509091024.dist-info/METADATA
youtrack_sdk-1.0.202509091024.dist-info/WHEEL
youtrack_sdk-1.0.202509091024.dist-info/RECORD
