Metadata-Version: 2.3
Name: youtrack-sdk
Version: 1.0.202509091024
Summary: YouTrack SDK
License: MIT
Keywords: youtrack,sdk
Author: moneymeets
Author-email: service@moneymeets.com
Requires-Python: >=3.12
Classifier: Development Status :: 5 - Production/Stable
Classifier: Intended Audience :: Developers
Classifier: Programming Language :: Python :: 3
Classifier: Programming Language :: Python :: 3.12
Classifier: Topic :: Software Development :: Libraries :: Python Modules
Classifier: License :: OSI Approved :: MIT License
Requires-Dist: pydantic
Requires-Dist: requests
Project-URL: Repository, https://github.com/moneymeets/youtrack-sdk
